cssformatter.py
zformat.py
zformat-0.9.2.dist-info/DESCRIPTION.rst
zformat-0.9.2.dist-info/METADATA
zformat-0.9.2.dist-info/RECORD
zformat-0.9.2.dist-info/WHEEL
zformat-0.9.2.dist-info/entry_points.txt
zformat-0.9.2.dist-info/metadata.json
zformat-0.9.2.dist-info/top_level.txt
