Metadata-Version: 2.0
Name: zformat
Version: 0.9.2
Summary: An opinionated CLI format checker, formatter and minimizer for JavaScript and CSS.
Home-page: https://github.com/joshsziegler/z-format
Author: Josh Ziegler
Author-email: josh.s.ziegler@gmail.com
License: MIT
Platform: UNKNOWN
Requires-Python: >=3.4
Requires-Dist: jsbeautifier (>=1.6)
Requires-Dist: jsmin (>=2.2)
